pyvoxsurf.cp38-win_amd64.pyd
pyvoxsurf-1.0.7.dist-info/LICENSE
pyvoxsurf-1.0.7.dist-info/METADATA
pyvoxsurf-1.0.7.dist-info/WHEEL
pyvoxsurf-1.0.7.dist-info/top_level.txt
pyvoxsurf-1.0.7.dist-info/RECORD
