Metadata-Version: 2.1
Name: pyvoxsurf
Version: 1.0.7
Summary: A Python C++ extension based on VoxSurf for voxelization of 3D meshes.
Home-page: https://github.com/jttoombs/PyVoxSurf
Author: Joseph Toombs
Author-email: jtoombs719@gmail.com
License: UNKNOWN
Platform: UNKNOWN
